RNA/RNA.py
RNA/_RNA.cp314-win_amd64.pyd
RNA/__init__.py
ViennaRNA/__init__.py
viennarna-2.7.1.dist-info/licenses/AUTHORS
viennarna-2.7.1.dist-info/licenses/COPYING
viennarna-2.7.1.dist-info/METADATA
viennarna-2.7.1.dist-info/WHEEL
viennarna-2.7.1.dist-info/top_level.txt
viennarna-2.7.1.dist-info/RECORD
