Metadata-Version: 2.4
Name: ViennaRNA
Version: 2.7.1
Summary: A library for the prediction and comparison of RNA secondary structures.
Author-email: Ronny Lorenz <ronny@tbi.univie.ac.at>, "Ivo L. Hofacker" <ivo@tbi.univie.ac.at>
Maintainer-email: Ronny Lorenz <rna@tbi.univie.ac.at>, Ayaan Hossain <auh57@psu.edu>
License: 			 Disclaimer and Copyright
Project-URL: Homepage, https://www.tbi.univie.ac.at/RNA
Project-URL: Documentation, https://viennarna.readthedocs.io/
Project-URL: Bug Tracker, https://github.com/ViennaRNA/ViennaRNA/issues
Project-URL: Changelog, https://www.tbi.univie.ac.at/RNA/changelog.html
Keywords: synthetic,computational,biology,genetic,DNA,RNA,secondary,structure,prediction,minimum,free,energy,centroid,subopt,mfe,ViennaRNA,dynamic,partition function,modified base,constraints,programming
Classifier: Development Status :: 5 - Production/Stable
Classifier: Programming Language :: Python :: 3
Classifier: Operating System :: Unix
Classifier: Operating System :: MacOS :: MacOS X
Classifier: Intended Audience :: Science/Research
Classifier: Intended Audience :: Education
Classifier: Programming Language :: Python
Classifier: Topic :: Scientific/Engineering
Classifier: Topic :: Scientific/Engineering :: Bio-Informatics
Classifier: Topic :: Scientific/Engineering :: Chemistry
Requires-Python: >=3.8
License-File: COPYING
License-File: AUTHORS
Dynamic: description
Dynamic: description-content-type
Dynamic: license-file
